placeload/__init__.py
placeload-0.4.0.dist-info/AUTHORS
placeload-0.4.0.dist-info/LICENSE
placeload-0.4.0.dist-info/METADATA
placeload-0.4.0.dist-info/WHEEL
placeload-0.4.0.dist-info/entry_points.txt
placeload-0.4.0.dist-info/pbr.json
placeload-0.4.0.dist-info/top_level.txt
placeload-0.4.0.dist-info/RECORD
