Metadata-Version: 2.1
Name: placeload
Version: 0.4.0
Summary: Async create many resource providers
Home-page: https://github.com/cdent/placeload
Author: Chris Dent
Author-email: cdent@anticdent.org
License: Apache-2
Platform: UNKNOWN
Classifier: Intended Audience :: Developers
Classifier: License :: OSI Approved :: Apache Software License
Classifier: Operating System :: POSIX
Classifier: Programming Language :: Python
Classifier: Programming Language :: Python :: 3
Classifier: Programming Language :: Python :: 3.5
Classifier: Programming Language :: Python :: 3.6
Classifier: Programming Language :: Python :: 3.7
Requires-Dist: aiohttp
Requires-Dist: cchardet
Requires-Dist: aiodns
Requires-Dist: os-traits
